lpbuildd/__init__.py
lpbuildd/binarypackage.py
lpbuildd/buildd-slave.tac
lpbuildd/builder.py
lpbuildd/charm.py
lpbuildd/check_implicit_pointer_functions.py
lpbuildd/ci.py
lpbuildd/debian.py
lpbuildd/livefs.py
lpbuildd/log.py
lpbuildd/oci.py
lpbuildd/proxy.py
lpbuildd/snap.py
lpbuildd/sourcepackagerecipe.py
lpbuildd/translationtemplates.py
lpbuildd/util.py
lpbuildd/pottery/__init__.py
lpbuildd/pottery/intltool.py
lpbuildd/pottery/tests/__init__.py
lpbuildd/pottery/tests/test_intltool.py
lpbuildd/target/__init__.py
lpbuildd/target/apt.py
lpbuildd/target/backend.py
lpbuildd/target/build_charm.py
lpbuildd/target/build_livefs.py
lpbuildd/target/build_oci.py
lpbuildd/target/build_snap.py
lpbuildd/target/chroot.py
lpbuildd/target/cli.py
lpbuildd/target/generate_translation_templates.py
lpbuildd/target/lifecycle.py
lpbuildd/target/lxd.py
lpbuildd/target/operation.py
lpbuildd/target/proxy.py
lpbuildd/target/run_ci.py
lpbuildd/target/snapstore.py
lpbuildd/target/status.py
lpbuildd/target/vcs.py
lpbuildd/target/tests/__init__.py
lpbuildd/target/tests/matchers.py
lpbuildd/target/tests/test_apt.py
lpbuildd/target/tests/test_build_charm.py
lpbuildd/target/tests/test_build_livefs.py
lpbuildd/target/tests/test_build_oci.py
lpbuildd/target/tests/test_build_snap.py
lpbuildd/target/tests/test_chroot.py
lpbuildd/target/tests/test_generate_translation_templates.py
lpbuildd/target/tests/test_lifecycle.py
lpbuildd/target/tests/test_lxd.py
lpbuildd/target/tests/test_operation.py
lpbuildd/target/tests/test_run_ci.py
lpbuildd/target/tests/testfixtures.py
lpbuildd/tests/__init__.py
lpbuildd/tests/buildd-slave-test.conf
lpbuildd/tests/buildlog
lpbuildd/tests/buildlog.long
lpbuildd/tests/dummy_templates.tar.gz
lpbuildd/tests/fakebuilder.py
lpbuildd/tests/harness.py
lpbuildd/tests/matchers.py
lpbuildd/tests/oci_tarball.py
lpbuildd/tests/test_1.diff
lpbuildd/tests/test_2.diff
lpbuildd/tests/test_binarypackage.py
lpbuildd/tests/test_buildd.py
lpbuildd/tests/test_builder.py
launchpad_buildd-206.dist-info/LICENSE
launchpad_buildd-206.dist-info/METADATA
launchpad_buildd-206.dist-info/WHEEL
launchpad_buildd-206.dist-info/top_level.txt
launchpad_buildd-206.dist-info/RECORD
