Metadata-Version: 2.1
Name: launchpad-buildd
Version: 206
Summary: Launchpad buildd slave
Home-page: https://launchpad.net/launchpad-buildd
Maintainer: Launchpad Developers
Maintainer-email: launchpad-dev@lists.launchpad.net
License: Affero GPL v3
Platform: UNKNOWN
License-File: LICENSE
Requires-Dist: python-debian (>=0.1.23)
Requires-Dist: requests
Requires-Dist: six
Requires-Dist: Twisted
Requires-Dist: zope.interface
Provides-Extra: lxd
Requires-Dist: netaddr ; extra == 'lxd'
Requires-Dist: pylxd ; extra == 'lxd'
